gripy-0.0.6.dist-info/WHEEL
gripy-0.0.6.dist-info/METADATA
gripy-0.0.6.dist-info/top_level.txt
gripy-0.0.6.dist-info/RECORD
gripy-0.0.6.dist-info/LICENSE
gripy.libs/libgfortran-ed201abd.so.3.0.0
gripy/libg2.cpython-39-x86_64-linux-gnu.so
gripy/binary.py
gripy/grib2.py
gripy/grids.py
gripy/__init__.py
gripy/g2pylib.py
gripy/legacy/gbits.py
gripy/legacy/comunpack.py
gripy/legacy/__init__.py
gripy/legacy/py3grib2.py
gripy/tables/__init__.py
gripy/tables/ncep/1/1.4.json
gripy/tables/ncep/1/1.3.json
gripy/tables/ncep/1/1.2.json
gripy/tables/ncep/1/1.1.json
gripy/tables/ncep/1/1.0.json
gripy/tables/ncep/4/4.2.10.0.json
gripy/tables/ncep/4/4.2.4.7.json
gripy/tables/ncep/4/4.2.2.5.json
gripy/tables/ncep/4/4.2.1.1.json
gripy/tables/ncep/4/4.212.json
gripy/tables/ncep/4/4.2.1.0.json
gripy/tables/ncep/4/4.2.10.3.json
gripy/tables/ncep/4/4.2.4.8.json
gripy/tables/ncep/4/4.2.10.4.json
gripy/tables/ncep/4/4.213.json
gripy/tables/ncep/4/4.2.3.1.json
gripy/tables/ncep/4/4.2.0.3.json
gripy/tables/ncep/4/4.2.2.1.json
gripy/tables/ncep/4/4.202.json
gripy/tables/ncep/4/4.221.json
gripy/tables/ncep/4/4.206.json
gripy/tables/ncep/4/4.2.0.192.json
gripy/tables/ncep/4/4.2.0.2.json
gripy/tables/ncep/4/4.209.json
gripy/tables/ncep/4/4.2.0.14.json
gripy/tables/ncep/4/4.230.json
gripy/tables/ncep/4/4.208.json
gripy/tables/ncep/4/4.217.json
gripy/tables/ncep/4/4.2.3.192.json
gripy/tables/ncep/4/4.2.4.3.json
gripy/tables/ncep/4/4.2.209.10.json
gripy/tables/ncep/4/4.203.json
gripy/tables/ncep/4/4.2.0.15.json
gripy/tables/ncep/4/4.2.2.3.json
gripy/tables/ncep/4/4.7.json
gripy/tables/ncep/4/4.2.json
gripy/tables/ncep/4/4.2.0.13.json
gripy/tables/ncep/4/4.2.0.7.json
gripy/tables/ncep/4/4.2.2.0.json
gripy/tables/ncep/4/4.201.json
gripy/tables/ncep/4/4.13.json
gripy/tables/ncep/4/4.14.json
gripy/tables/ncep/4/4.207.json
gripy/tables/ncep/4/4.2.4.1.json
gripy/tables/ncep/4/4.223.json
gripy/tables/ncep/4/4.2.209.8.json
gripy/tables/ncep/4/4.220.json
gripy/tables/ncep/4/4.2.209.3.json
gripy/tables/ncep/4/4.2.4.4.json
gripy/tables/ncep/4/4.2.209.6.json
gripy/tables/ncep/4/4.9.json
