Metadata-Version: 2.1
Name: gripy
Version: 0.0.6
Summary: Grib Reader In PYthon.,
Home-page: https://github.com/abrammer/gripy
Author: abrammer
Author-email: alan.brammer@gmail.com
License: UNKNOWN
Platform: UNKNOWN
Requires-Dist: numpy
